backlog/__init__.py
backlog/attachment.py
backlog/base.py
backlog/category.py
backlog/custom_field.py
backlog/git.py
backlog/issue.py
backlog/project.py
backlog/user.py
backlog/wiki.py
python_backlog-0.7.4.dist-info/LICENSE
python_backlog-0.7.4.dist-info/METADATA
python_backlog-0.7.4.dist-info/WHEEL
python_backlog-0.7.4.dist-info/top_level.txt
python_backlog-0.7.4.dist-info/RECORD
