Metadata-Version: 2.1
Name: python-backlog
Version: 0.7.4
Summary: Backlog API v2 wrapper
Home-page: https://github.com/hassaku63/pbl
Author: hassaku63
Author-email: hassaku63@gmail.com
License: MIT
Project-URL: Source, https://github.com/hassaku63/pbl
Keywords: nulab backlog
Classifier: Development Status :: 4 - Beta
Classifier: Programming Language :: Python
Classifier: Programming Language :: Python :: 3.8
Classifier: Programming Language :: Python :: 3.9
Classifier: Programming Language :: Python :: 3.10
Classifier: Programming Language :: Python :: 3.11
Classifier: Natural Language :: Japanese
Requires-Python: >=3.8
License-File: LICENSE
Requires-Dist: requests ~=2.32.2
